grabber/__init__.py
grabber/grabber.py
grabber-0.1.0.dist-info/DESCRIPTION.rst
grabber-0.1.0.dist-info/entry_points.txt
grabber-0.1.0.dist-info/METADATA
grabber-0.1.0.dist-info/metadata.json
grabber-0.1.0.dist-info/RECORD
grabber-0.1.0.dist-info/top_level.txt
grabber-0.1.0.dist-info/WHEEL
