Metadata-Version: 1.1
Name: grabber
Version: 0.1.0
Summary: grabber: periodically grabs a picture of your screen
Home-page: https://github.com/bnomis/grabber
Author: Simon Blanchard
Author-email: bnomis@gmail.com
License: MIT
Keywords: search,text,find
Platform: macosx
Classifier: Development Status :: 5 - Production/Stable
Classifier: Environment :: Console
Classifier: Environment :: MacOS X
Classifier: Intended Audience :: Developers
Classifier: Intended Audience :: System Administrators
Classifier: License :: OSI Approved :: MIT License
Classifier: Natural Language :: English
Classifier: Operating System :: MacOS :: MacOS X
Classifier: Programming Language :: Python :: 2.7
Classifier: Programming Language :: Python :: 3.4
Classifier: Topic :: Multimedia :: Graphics :: Capture :: Screen Capture
Classifier: Topic :: Security
Classifier: Topic :: System :: Monitoring
Classifier: Topic :: System :: Systems Administration
Classifier: Topic :: Utilities
